[{"produced":[-11,-15,14,3,-22,16],"consumed":[-7,-16,4,2,-21,7,4,-21,8]},{"produced":[-11,-15,16,3,-22,16],"consumed":[-24,-20,30,-7,-16,3,2,-21,7]},{"produced":[-11,-15,12,3,-22,18],"consumed":[-24,-20,10,-7,-16,3,2,-21,6]},{"produced":[-11,-15,2],"consumed":[-7,-16,1,2,-21,3]},{"produced":[-11,-15,2,3,-22,2],"consumed":[-24,-20,20]},{"produced":[-11,-15,14,3,-22,14],"consumed":[-24,-20,20,4,-21,12]},{"produced":[-11,-15,12,3,-22,16],"consumed":[-24,-20,4]},{"produced":[],"consumed":[4,-21,4]},{"produced":[],"consumed":[]},{"produced":[-11,-15,6,3,-22,6],"consumed":[4,-21,12]},{"produced":[-11,-15,4,3,-22,6],"consumed":[-7,-16,2,2,-21,5]},{"produced":[-11,-15,8,3,-22,8],"consumed":[-7,-16,4,2,-21,8]},{"produced":[],"consumed":[-7,-16,1,2,-21,1,4,-21,8]},{"produced":[],"consumed":[]},{"produced":[],"consumed":[]},{"produced":[],"consumed":[]},{"produced":[],"consumed":[]},{"produced":[],"consumed":[]},{"produced":[],"consumed":[]},{"produced":[],"consumed":[]},{"produced":[],"consumed":[]},{"produced":[],"consumed":[]},{"produced":[],"consumed":[]},{"produced":[],"consumed":[]},{"produced":[],"consumed":[]},{"produced":[],"consumed":[]},{"produced":[],"consumed":[]},{"produced":[],"consumed":[]},{"produced":[],"consumed":[]},{"produced":[],"consumed":[]},{"produced":[],"consumed":[]},{"produced":[],"consumed":[]},{"produced":[],"consumed":[]},{"produced":[],"consumed":[]},{"produced":[],"consumed":[]},{"produced":[],"consumed":[]},{"produced":[],"consumed":[]},{"produced":[],"consumed":[]},{"produced":[],"consumed":[]},{"produced":[],"consumed":[]},{"produced":[],"consumed":[]},{"produced":[],"consumed":[]},{"produced":[],"consumed":[]},{"produced":[],"consumed":[]},{"produced":[],"consumed":[]},{"produced":[],"consumed":[]},{"produced":[],"consumed":[]},{"produced":[],"consumed":[]},{"produced":[],"consumed":[]},{"produced":[],"consumed":[]},{"produced":[],"consumed":[]},{"produced":[],"consumed":[]},{"produced":[],"consumed":[]},{"produced":[],"consumed":[]},{"produced":[],"consumed":[]},{"produced":[],"consumed":[]},{"produced":[],"consumed":[]},{"produced":[],"consumed":[]},{"produced":[],"consumed":[]},{"produced":[],"consumed":[]},{"produced":[],"consumed":[]},{"produced":[],"consumed":[]},{"produced":[],"consumed":[]},{"produced":[],"consumed":[]},{"produced":[],"consumed":[]},{"produced":[],"consumed":[]},{"produced":[],"consumed":[]},{"produced":[],"consumed":[]},{"produced":[],"consumed":[]},{"produced":[],"consumed":[]},{"produced":[],"consumed":[]},{"produced":[],"consumed":[]},{"produced":[],"consumed":[]},{"produced":[],"consumed":[]},{"produced":[],"consumed":[]},{"produced":[],"consumed":[]},{"produced":[],"consumed":[]},{"produced":[],"consumed":[]},{"produced":[],"consumed":[]},{"produced":[],"consumed":[]},{"produced":[],"consumed":[]},{"produced":[],"consumed":[]},{"produced":[],"consumed":[]},{"produced":[],"consumed":[]},{"produced":[],"consumed":[]},{"produced":[],"consumed":[]},{"produced":[],"consumed":[]},{"produced":[],"consumed":[]},{"produced":[],"consumed":[]},{"produced":[],"consumed":[]},{"produced":[],"consumed":[]},{"produced":[],"consumed":[]},{"produced":[],"consumed":[]},{"produced":[],"consumed":[]},{"produced":[],"consumed":[]},{"produced":[],"consumed":[]},{"produced":[],"consumed":[]},{"produced":[],"consumed":[]},{"produced":[],"consumed":[]},{"produced":[],"consumed":[]},{"produced":[],"consumed":[]},{"produced":[],"consumed":[]},{"produced":[],"consumed":[]},{"produced":[],"consumed":[]},{"produced":[],"consumed":[]},{"produced":[],"consumed":[]},{"produced":[],"consumed":[]},{"produced":[],"consumed":[]},{"produced":[],"consumed":[]},{"produced":[],"consumed":[]},{"produced":[],"consumed":[]},{"produced":[],"consumed":[]},{"produced":[],"consumed":[]},{"produced":[],"consumed":[]},{"produced":[],"consumed":[]},{"produced":[-11,-15,2,3,-22,2],"consumed":[4,-21,4]},{"produced":[-11,-15,6,3,-22,4],"consumed":[]},{"produced":[],"consumed":[]},{"produced":[3,-22,2],"consumed":[-24,-20,26]},{"produced":[-11,-15,14,3,-22,12],"consumed":[-24,-20,10]},{"produced":[],"consumed":[]},{"produced":[3,-22,8],"consumed":[-24,-20,10]},{"produced":[-11,-15,6],"consumed":[-24,-20,10]},{"produced":[-11,-15,2],"consumed":[]},{"produced":[-11,-15,8,3,-22,8],"consumed":[-24,-20,20]},{"produced":[-11,-15,4,3,-22,6],"consumed":[-24,-20,12]},{"produced":[-11,-15,14,3,-22,16],"consumed":[-24,-20,36]},{"produced":[-11,-15,6],"consumed":[]},{"produced":[-11,-15,12,3,-22,10],"consumed":[-24,-20,12]},{"produced":[3,-22,8],"consumed":[-24,-20,10]},{"produced":[],"consumed":[]},{"produced":[],"consumed":[]},{"produced":[],"consumed":[]},{"produced":[],"consumed":[]},{"produced":[],"consumed":[]},{"produced":[],"consumed":[]},{"produced":[],"consumed":[]},{"produced":[],"consumed":[]},{"produced":[],"consumed":[]},{"produced":[],"consumed":[]},{"produced":[],"consumed":[]},{"produced":[],"consumed":[]},{"produced":[],"consumed":[]},{"produced":[],"consumed":[]},{"produced":[],"consumed":[]},{"produced":[],"consumed":[]},{"produced":[],"consumed":[]},{"produced":[],"consumed":[]},{"produced":[],"consumed":[]},{"produced":[],"consumed":[]},{"produced":[],"consumed":[]},{"produced":[],"consumed":[]},{"produced":[],"consumed":[]},{"produced":[],"consumed":[]},{"produced":[],"consumed":[]},{"produced":[],"consumed":[]},{"produced":[],"consumed":[]},{"produced":[],"consumed":[]},{"produced":[],"consumed":[]},{"produced":[],"consumed":[]},{"produced":[],"consumed":[]},{"produced":[],"consumed":[]},{"produced":[],"consumed":[]},{"produced":[],"consumed":[]},{"produced":[],"consumed":[]},{"produced":[],"consumed":[]},{"produced":[],"consumed":[]},{"produced":[],"consumed":[]},{"produced":[],"consumed":[]},{"produced":[],"consumed":[]},{"produced":[],"consumed":[]},{"produced":[],"consumed":[]},{"produced":[],"consumed":[]},{"produced":[],"consumed":[]},{"produced":[],"consumed":[]},{"produced":[],"consumed":[]},{"produced":[],"consumed":[]},{"produced":[],"consumed":[]},{"produced":[],"consumed":[]},{"produced":[],"consumed":[]},{"produced":[],"consumed":[]},{"produced":[],"consumed":[]},{"produced":[],"consumed":[]},{"produced":[],"consumed":[]},{"produced":[],"consumed":[]},{"produced":[],"consumed":[]},{"produced":[],"consumed":[]},{"produced":[],"consumed":[]},{"produced":[],"consumed":[]},{"produced":[],"consumed":[]},{"produced":[],"consumed":[]},{"produced":[],"consumed":[]},{"produced":[],"consumed":[]},{"produced":[],"consumed":[]},{"produced":[],"consumed":[]},{"produced":[],"consumed":[]},{"produced":[],"consumed":[]},{"produced":[],"consumed":[]},{"produced":[],"consumed":[]},{"produced":[],"consumed":[]},{"produced":[],"consumed":[]},{"produced":[],"consumed":[]},{"produced":[],"consumed":[]},{"produced":[],"consumed":[]},{"produced":[],"consumed":[]},{"produced":[],"consumed":[]},{"produced":[],"consumed":[]},{"produced":[],"consumed":[]},{"produced":[],"consumed":[]},{"produced":[],"consumed":[]},{"produced":[],"consumed":[]},{"produced":[],"consumed":[]},{"produced":[],"consumed":[]},{"produced":[],"consumed":[]},{"produced":[],"consumed":[]},{"produced":[],"consumed":[]},{"produced":[],"consumed":[]},{"produced":[],"consumed":[]},{"produced":[],"consumed":[]},{"produced":[-11,-15,8,3,-22,8],"consumed":[-24,-20,16]},{"produced":[],"consumed":[]},{"produced":[-11,-15,8,3,-22,6],"consumed":[-24,-20,10,4,-21,4]},{"produced":[-11,-15,12,3,-22,12],"consumed":[-24,-20,24,-7,-16,3,2,-21,5,4,-21,4]},{"produced":[-11,-15,10,3,-22,12],"consumed":[-7,-16,1,2,-21,4,4,-21,8]},{"produced":[-11,-15,16,3,-22,10],"consumed":[-24,-20,30,4,-21,4]},{"produced":[-11,-15,10,3,-22,14],"consumed":[-24,-20,36,-7,-16,4,2,-21,7,4,-21,16]},{"produced":[-11,-15,20,3,-22,18],"consumed":[-24,-20,14,-7,-16,5,2,-21,9,4,-21,8]},{"produced":[-11,-15,12,3,-22,20],"consumed":[-7,-16,4,2,-21,9,4,-21,4]},{"produced":[-11,-15,4,3,-22,20],"consumed":[-24,-20,24,-7,-16,2,2,-21,4,4,-21,4]},{"produced":[-11,-15,14,3,-22,20],"consumed":[4,-21,8]},{"produced":[-11,-15,6],"consumed":[-24,-20,4,4,-21,4]},{"produced":[-11,-15,14,3,-22,14],"consumed":[-24,-20,16,4,-21,8]},{"produced":[-11,-15,2,3,-22,4],"consumed":[-24,-20,16,4,-21,16]},{"produced":[-11,-15,14,3,-22,16],"consumed":[-24,-20,10,4,-21,8]},{"produced":[-11,-15,10,3,-22,8],"consumed":[4,-21,4]},{"produced":[3,-22,6],"consumed":[-24,-20,16]},{"produced":[],"consumed":[]},{"produced":[-11,-15,10,3,-22,12],"consumed":[-24,-20,38]},{"produced":[-11,-15,18,3,-22,20],"consumed":[-24,-20,16]},{"produced":[3,-22,2],"consumed":[4,-21,4]},{"produced":[-11,-15,10,3,-22,8],"consumed":[-24,-20,10,4,-21,8]},{"produced":[3,-22,2],"consumed":[4,-21,4]},{"produced":[-11,-15,12,3,-22,10],"consumed":[-24,-20,10,4,-21,4]},{"produced":[-11,-15,12,3,-22,12],"consumed":[-24,-20,40,4,-21,16]},{"produced":[-11,-15,10,3,-22,12],"consumed":[]},{"produced":[-11,-15,10,3,-22,6],"consumed":[-24,-20,14]},{"produced":[-11,-15,2,3,-22,4],"consumed":[-24,-20,14]},{"produced":[-11,-15,6,3,-22,8],"consumed":[]},{"produced":[],"consumed":[-24,-20,16]},{"produced":[],"consumed":[]},{"produced":[-11,-15,6,3,-22,6],"consumed":[-24,-20,26,4,-21,8]},{"produced":[-11,-15,20,3,-22,20],"consumed":[-24,-20,14]},{"produced":[-11,-15,6,3,-22,4],"consumed":[4,-21,12]},{"produced":[-11,-15,14,3,-22,10],"consumed":[-24,-20,20]},{"produced":[-11,-15,6,3,-22,10],"consumed":[-24,-20,16]},{"produced":[-11,-15,4,3,-22,4],"consumed":[-24,-20,28]},{"produced":[-11,-15,20,3,-22,18],"consumed":[4,-21,8]},{"produced":[-11,-15,6,3,-22,6],"consumed":[-24,-20,12]},{"produced":[-11,-15,2,3,-22,4],"consumed":[-24,-20,10]},{"produced":[-11,-15,4,3,-22,2],"consumed":[]},{"produced":[-11,-15,12,3,-22,10],"consumed":[-24,-20,20]},{"produced":[3,-22,8],"consumed":[-24,-20,16]},{"produced":[],"consumed":[]},{"produced":[-11,-15,10,3,-22,10],"consumed":[-24,-20,10]},{"produced":[-11,-15,16,3,-22,16],"consumed":[-24,-20,220]},{"produced":[-11,-15,18,3,-22,18],"consumed":[-24,-20,74]},{"produced":[-11,-15,20,3,-22,20],"consumed":[-24,-20,28]},{"produced":[-11,-15,20,3,-22,20],"consumed":[-24,-20,50]},{"produced":[-11,-15,18,3,-22,20],"consumed":[-24,-20,14]},{"produced":[-11,-15,20,3,-22,18],"consumed":[-24,-20,12]},{"produced":[-11,-15,18,3,-22,20],"consumed":[-24,-20,16]},{"produced":[-11,-15,8,3,-22,20],"consumed":[4,-21,24]},{"produced":[-11,-15,10,3,-22,18],"consumed":[]},{"produced":[-11,-15,10,3,-22,12],"consumed":[-24,-20,18]},{"produced":[-11,-15,10,3,-22,8],"consumed":[]},{"produced":[-11,-15,18,3,-22,16],"consumed":[]},{"produced":[-11,-15,10,3,-22,12],"consumed":[]},{"produced":[-11,-15,6,3,-22,6],"consumed":[]},{"produced":[],"consumed":[]},{"produced":[],"consumed":[]},{"produced":[],"consumed":[]},{"produced":[-11,-15,10,3,-22,10],"consumed":[-24,-20,12]},{"produced":[],"consumed":[]},{"produced":[],"consumed":[]},{"produced":[],"consumed":[]},{"produced":[],"consumed":[]},{"produced":[-11,-15,6,3,-22,6],"consumed":[-24,-20,14]},{"produced":[],"consumed":[]},{"produced":[],"consumed":[]},{"produced":[],"consumed":[]},{"produced":[],"consumed":[]},{"produced":[],"consumed":[]},{"produced":[],"consumed":[]},{"produced":[],"consumed":[]},{"produced":[],"consumed":[]},{"produced":[],"consumed":[-24,-20,14]},{"produced":[-11,-15,8,3,-22,10],"consumed":[]},{"produced":[],"consumed":[]},{"produced":[],"consumed":[]},{"produced":[-11,-15,12,3,-22,12],"consumed":[-24,-20,16,4,-21,16]},{"produced":[-11,-15,4,3,-22,6],"consumed":[4,-21,4]},{"produced":[],"consumed":[]},{"produced":[],"consumed":[]},{"produced":[-11,-15,2,3,-22,4],"consumed":[-24,-20,16]},{"produced":[-11,-15,12,3,-22,12],"consumed":[-24,-20,14]},{"produced":[],"consumed":[]},{"produced":[],"consumed":[]},{"produced":[],"consumed":[]},{"produced":[],"consumed":[]},{"produced":[],"consumed":[]},{"produced":[-11,-15,2],"consumed":[-24,-20,16]},{"produced":[-11,-15,8,3,-22,10],"consumed":[]},{"produced":[-11,-15,8,3,-22,8],"consumed":[-24,-20,18]},{"produced":[],"consumed":[]},{"produced":[],"consumed":[]},{"produced":[-11,-15,6,3,-22,6],"consumed":[-24,-20,12]},{"produced":[],"consumed":[]},{"produced":[],"consumed":[]},{"produced":[],"consumed":[]},{"produced":[],"consumed":[]},{"produced":[-11,-15,8,3,-22,4],"consumed":[-24,-20,14]},{"produced":[-11,-15,2,3,-22,4],"consumed":[-24,-20,6]},{"produced":[-11,-15,10,3,-22,8],"consumed":[-24,-20,16]},{"produced":[-11,-15,4,3,-22,4],"consumed":[-24,-20,18]},{"produced":[-11,-15,4,3,-22,4],"consumed":[]},{"produced":[-11,-15,8,3,-22,8],"consumed":[-24,-20,14]},{"produced":[-11,-15,8,3,-22,4],"consumed":[-24,-20,32]},{"produced":[-11,-15,8,3,-22,8],"consumed":[-24,-20,14]},{"produced":[-11,-15,16,3,-22,16],"consumed":[-24,-20,16]},{"produced":[],"consumed":[]},{"produced":[-11,-15,6],"consumed":[-24,-20,10]},{"produced":[],"consumed":[]},{"produced":[-11,-15,6,3,-22,6],"consumed":[-24,-20,14]},{"produced":[-11,-15,2,3,-22,2],"consumed":[]},{"produced":[],"consumed":[-24,-20,14]},{"produced":[-11,-15,12,3,-22,10],"consumed":[-24,-20,2]},{"produced":[-11,-15,4,3,-22,6],"consumed":[-24,-20,20,4,-21,8]},{"produced":[-11,-15,20,3,-22,18],"consumed":[-24,-20,16,4,-21,12]},{"produced":[3,-22,2],"consumed":[]},{"produced":[-11,-15,8,3,-22,10],"consumed":[-24,-20,10]},{"produced":[],"consumed":[]},{"produced":[],"consumed":[]},{"produced":[-11,-15,6],"consumed":[-24,-20,14]},{"produced":[-11,-15,2,3,-22,8],"consumed":[-24,-20,20]},{"produced":[-11,-15,8,3,-22,8],"consumed":[-24,-20,10]},{"produced":[3,-22,2],"consumed":[]},{"produced":[],"consumed":[]},{"produced":[],"consumed":[]},{"produced":[-11,-15,4,3,-22,6],"consumed":[4,-21,8]},{"produced":[-11,-15,6,3,-22,6],"consumed":[4,-21,8]},{"produced":[],"consumed":[]},{"produced":[-11,-15,6,3,-22,6],"consumed":[-24,-20,10]},{"produced":[],"consumed":[]},{"produced":[3,-22,2],"consumed":[-24,-20,18]},{"produced":[-11,-15,10,3,-22,6],"consumed":[]},{"produced":[],"consumed":[]},{"produced":[],"consumed":[]},{"produced":[],"consumed":[-24,-20,12]},{"produced":[3,-22,8],"consumed":[]},{"produced":[],"consumed":[]},{"produced":[],"consumed":[]},{"produced":[],"consumed":[]},{"produced":[],"consumed":[]},{"produced":[],"consumed":[]},{"produced":[],"consumed":[]},{"produced":[],"consumed":[-24,-20,2]},{"produced":[-11,-15,10,3,-22,8],"consumed":[-24,-20,12,4,-21,16]},{"produced":[],"consumed":[]},{"produced":[],"consumed":[]},{"produced":[],"consumed":[]},{"produced":[-11,-15,4,3,-22,4],"consumed":[-24,-20,10]},{"produced":[-11,-15,6,3,-22,8],"consumed":[-24,-20,10]},{"produced":[],"consumed":[]},{"produced":[],"consumed":[-24,-20,10]},{"produced":[-11,-15,20,3,-22,20],"consumed":[-24,-20,16,4,-21,12]},{"produced":[3,-22,2],"consumed":[]},{"produced":[-11,-15,8,3,-22,12],"consumed":[-24,-20,16]},{"produced":[],"consumed":[-24,-20,4]},{"produced":[],"consumed":[]},{"produced":[-11,-15,8,3,-22,6],"consumed":[-24,-20,20]},{"produced":[-11,-15,2,3,-22,4],"consumed":[]},{"produced":[-11,-15,12,3,-22,14],"consumed":[-24,-20,20,4,-21,12]},{"produced":[-11,-15,6,3,-22,6],"consumed":[-24,-20,10]},{"produced":[],"consumed":[]},{"produced":[-11,-15,14,3,-22,12],"consumed":[-24,-20,34]},{"produced":[-11,-15,4,3,-22,10],"consumed":[-24,-20,16]},{"produced":[-11,-15,8,3,-22,4],"consumed":[]},{"produced":[-11,-15,10,3,-22,10],"consumed":[4,-21,16]},{"produced":[],"consumed":[]},{"produced":[],"consumed":[-24,-20,16]},{"produced":[-11,-15,10,3,-22,10],"consumed":[]},{"produced":[-11,-15,6,3,-22,6],"consumed":[-24,-20,18]},{"produced":[-11,-15,10,3,-22,12],"consumed":[-24,-20,22]},{"produced":[3,-22,4],"consumed":[]},{"produced":[-11,-15,8],"consumed":[-24,-20,12]},{"produced":[-11,-15,6,3,-22,10],"consumed":[-24,-20,8]},{"produced":[],"consumed":[-24,-20,4]},{"produced":[],"consumed":[]},{"produced":[],"consumed":[]},{"produced":[-11,-15,6],"consumed":[-24,-20,4]},{"produced":[],"consumed":[]},{"produced":[-11,-15,8,3,-22,8],"consumed":[-24,-20,16,4,-21,12]},{"produced":[-11,-15,6,3,-22,6],"consumed":[4,-21,4]},{"produced":[],"consumed":[]},{"produced":[],"consumed":[]},{"produced":[],"consumed":[]},{"produced":[],"consumed":[]},{"produced":[],"consumed":[]},{"produced":[],"consumed":[]},{"produced":[],"consumed":[]},{"produced":[],"consumed":[]},{"produced":[],"consumed":[]},{"produced":[-11,-15,6,3,-22,6],"consumed":[-24,-20,10]},{"produced":[-11,-15,16,3,-22,16],"consumed":[-24,-20,34,4,-21,8]},{"produced":[-11,-15,4,3,-22,4],"consumed":[4,-21,8]},{"produced":[],"consumed":[]},{"produced":[],"consumed":[]},{"produced":[],"consumed":[]},{"produced":[],"consumed":[]},{"produced":[],"consumed":[]},{"produced":[],"consumed":[]},{"produced":[],"consumed":[]},{"produced":[],"consumed":[-24,-20,12]},{"produced":[-11,-15,12,3,-22,14],"consumed":[-24,-20,18]},{"produced":[-11,-15,8,3,-22,6],"consumed":[-24,-20,6]},{"produced":[-11,-15,16,3,-22,18],"consumed":[-24,-20,50,4,-21,12]},{"produced":[-11,-15,14,3,-22,14],"consumed":[]},{"produced":[],"consumed":[]},{"produced":[],"consumed":[]},{"produced":[],"consumed":[]},{"produced":[],"consumed":[]},{"produced":[],"consumed":[]},{"produced":[],"consumed":[]},{"produced":[],"consumed":[]},{"produced":[],"consumed":[]},{"produced":[],"consumed":[]},{"produced":[-11,-15,6,3,-22,6],"consumed":[-24,-20,14]},{"produced":[],"consumed":[]},{"produced":[],"consumed":[]},{"produced":[],"consumed":[]},{"produced":[],"consumed":[]},{"produced":[],"consumed":[]},{"produced":[],"consumed":[]},{"produced":[],"consumed":[]},{"produced":[3,-22,2],"consumed":[-24,-20,8]},{"produced":[-11,-15,10,3,-22,10],"consumed":[-24,-20,8]},{"produced":[-11,-15,10,3,-22,10],"consumed":[-24,-20,20]},{"produced":[],"consumed":[]},{"produced":[],"consumed":[]},{"produced":[],"consumed":[]},{"produced":[],"consumed":[]},{"produced":[],"consumed":[]},{"produced":[],"consumed":[]},{"produced":[],"consumed":[]},{"produced":[],"consumed":[]},{"produced":[],"consumed":[]},{"produced":[3,-22,6],"consumed":[-24,-20,14]},{"produced":[],"consumed":[]},{"produced":[-11,-15,14,3,-22,16],"consumed":[-24,-20,36,4,-21,8]},{"produced":[-11,-15,10,3,-22,10],"consumed":[]},{"produced":[],"consumed":[]},{"produced":[],"consumed":[]},{"produced":[],"consumed":[]},{"produced":[],"consumed":[]},{"produced":[3,-22,6],"consumed":[-24,-20,16]},{"produced":[-11,-15,8,3,-22,14],"consumed":[-24,-20,14]},{"produced":[],"consumed":[]},{"produced":[],"consumed":[]},{"produced":[],"consumed":[]},{"produced":[],"consumed":[]},{"produced":[],"consumed":[]},{"produced":[],"consumed":[]},{"produced":[-11,-15,12,3,-22,14],"consumed":[-24,-20,52,4,-21,20]},{"produced":[-11,-15,18,3,-22,18],"consumed":[4,-21,8]},{"produced":[-11,-15,6,3,-22,8],"consumed":[]},{"produced":[],"consumed":[]},{"produced":[],"consumed":[]},{"produced":[],"consumed":[]},{"produced":[],"consumed":[]},{"produced":[-11,-15,10,3,-22,10],"consumed":[-24,-20,24]},{"produced":[3,-22,6],"consumed":[]},{"produced":[],"consumed":[]},{"produced":[],"consumed":[]},{"produced":[],"consumed":[]},{"produced":[],"consumed":[]},{"produced":[],"consumed":[]},{"produced":[],"consumed":[]},{"produced":[-11,-15,8],"consumed":[-24,-20,18]},{"produced":[-11,-15,10,3,-22,14],"consumed":[-24,-20,16]},{"produced":[],"consumed":[]},{"produced":[],"consumed":[]},{"produced":[],"consumed":[]},{"produced":[],"consumed":[]},{"produced":[],"consumed":[]},{"produced":[],"consumed":[]},{"produced":[-11,-15,8,3,-22,6],"consumed":[-24,-20,36,4,-21,4]},{"produced":[-11,-15,18,3,-22,20],"consumed":[-24,-20,28,4,-21,8]},{"produced":[-11,-15,12,3,-22,10],"consumed":[]},{"produced":[],"consumed":[]},{"produced":[],"consumed":[]},{"produced":[],"consumed":[]},{"produced":[],"consumed":[]},{"produced":[],"consumed":[]},{"produced":[],"consumed":[]},{"produced":[],"consumed":[]},{"produced":[],"consumed":[]},{"produced":[-11,-15,8,3,-22,8],"consumed":[-24,-20,16]},{"produced":[],"consumed":[]},{"produced":[],"consumed":[]},{"produced":[],"consumed":[]},{"produced":[],"consumed":[]},{"produced":[],"consumed":[]},{"produced":[-11,-15,8,3,-22,10],"consumed":[-24,-20,44,4,-21,16]},{"produced":[-11,-15,18,3,-22,18],"consumed":[]},{"produced":[],"consumed":[]},{"produced":[],"consumed":[]},{"produced":[],"consumed":[]},{"produced":[],"consumed":[]},{"produced":[],"consumed":[]},{"produced":[],"consumed":[]},{"produced":[],"consumed":[]},{"produced":[-11,-15,4,3,-22,4],"consumed":[-24,-20,6]},{"produced":[-11,-15,8,3,-22,8],"consumed":[-24,-20,20]},{"produced":[-11,-15,2],"consumed":[]},{"produced":[],"consumed":[]},{"produced":[],"consumed":[]},{"produced":[],"consumed":[]},{"produced":[],"consumed":[]},{"produced":[],"consumed":[]},{"produced":[],"consumed":[]},{"produced":[],"consumed":[]},{"produced":[-11,-15,12,3,-22,12],"consumed":[-24,-20,30]},{"produced":[-11,-15,6,3,-22,4],"consumed":[]},{"produced":[],"consumed":[]},{"produced":[],"consumed":[]},{"produced":[],"consumed":[]},{"produced":[],"consumed":[]},{"produced":[-11,-15,4,3,-22,6],"consumed":[-24,-20,10]},{"produced":[-11,-15,8,3,-22,8],"consumed":[-24,-20,40]},{"produced":[-11,-15,14,3,-22,12],"consumed":[]},{"produced":[],"consumed":[]},{"produced":[],"consumed":[]},{"produced":[],"consumed":[]},{"produced":[],"consumed":[]},{"produced":[],"consumed":[]},{"produced":[],"consumed":[-24,-20,14]},{"produced":[-11,-15,8,3,-22,10],"consumed":[-24,-20,16]},{"produced":[-11,-15,6,3,-22,4],"consumed":[]},{"produced":[],"consumed":[]},{"produced":[],"consumed":[]},{"produced":[],"consumed":[]},{"produced":[],"consumed":[]},{"produced":[],"consumed":[]},{"produced":[],"consumed":[]},{"produced":[-11,-15,8,3,-22,10],"consumed":[-24,-20,44,4,-21,12]},{"produced":[-11,-15,20,3,-22,20],"consumed":[-24,-20,18,4,-21,12]},{"produced":[-11,-15,12,3,-22,20],"consumed":[]},{"produced":[-11,-15,6],"consumed":[]},{"produced":[],"consumed":[]},{"produced":[],"consumed":[]},{"produced":[],"consumed":[]},{"produced":[],"consumed":[]},{"produced":[],"consumed":[]},{"produced":[-11,-15,8],"consumed":[-24,-20,12]},{"produced":[],"consumed":[]},{"produced":[],"consumed":[]},{"produced":[],"consumed":[]}]